{
    "transportLibrary": {
        "platformClientId": "<clientId (read `https://enmeshed.eu/integrate/connector-configuration#transportlibrary`)>",
        "platformClientSecret": "<clientSecret (read `https://enmeshed.eu/integrate/connector-configuration#transportlibrary`)>"
    },
    "database": {
        "connectionString": "mongodb://user:pass@mongodb:27017/?authSource=admin&readPreference=primary&ssl=false",
        "dbName": "demo"
    },
    "infrastructure": {
        "httpServer": {
            "apiKey": "<define-an-apiKey>"
        }
    },
    "modules": {
        "coreHttpApi": {
            "docs": {
                "enabled": true
            }
        }
    }
}
